Metadata-Version: 1.0
Name: TCPipelineUtils
Version: 1.0.2
Summary: Lib to encapsulate TC pipelines functions
Home-page: UNKNOWN
Author: Matheus Tramontini
Author-email: matheus.lopes@tc.com.br
License: UNKNOWN
Platform: UNKNOWN
